pyadvantech/__init__.py
pyadvantech/pyadvantech.py
pyadvantech-0.2.2.dist-info/LICENSE
pyadvantech-0.2.2.dist-info/METADATA
pyadvantech-0.2.2.dist-info/WHEEL
pyadvantech-0.2.2.dist-info/top_level.txt
pyadvantech-0.2.2.dist-info/RECORD
