Metadata-Version: 2.1
Name: pyadvantech
Version: 0.2.2
Summary: A custom USB driver for Advantech USB-4718
Home-page: https://github.com/Hieprong/pyadvantech
Author: Paul Weimer
Author-email: weimerpaul99@gmail.com
Classifier: Programming Language :: Python :: 3
Classifier: License :: OSI Approved :: MIT License
Classifier: Operating System :: OS Independent
License-File: LICENSE
Requires-Dist: matplotlib
Requires-Dist: libusb
Requires-Dist: pyusb
Requires-Dist: tqdm
Requires-Dist: numpy
